groundhog/__init__.py
groundhog/__version__.py
groundhog/consolidation/__init__.py
groundhog/consolidation/dissipation/__init__.py
groundhog/consolidation/dissipation/onedimensionalconsolidation.py
groundhog/consolidation/groundwaterflow/__init__.py
groundhog/consolidation/groundwaterflow/pumpingtests.py
groundhog/constitutivemodels/__init__.py
groundhog/constitutivemodels/cohesionless.py
groundhog/constitutivemodels/cohesive.py
groundhog/constitutivemodels/general.py
groundhog/constitutivemodels/rock.py
groundhog/deepfoundations/__init__.py
groundhog/deepfoundations/axialcapacity/__init__.py
groundhog/deepfoundations/axialcapacity/axcap.py
groundhog/deepfoundations/axialcapacity/debeer.py
groundhog/deepfoundations/axialcapacity/endbearing.py
groundhog/deepfoundations/axialcapacity/koppejan.py
groundhog/deepfoundations/axialcapacity/negativeskinfriction.py
groundhog/deepfoundations/axialcapacity/skinfriction.py
groundhog/deepfoundations/axialresponse/__init__.py
groundhog/deepfoundations/axialresponse/settlement.py
groundhog/deepfoundations/boreholestability/__init__.py
groundhog/deepfoundations/boreholestability/cavityexpansion.py
groundhog/deepfoundations/lateralresponse/__init__.py
groundhog/excavations/__init__.py
groundhog/excavations/basic.py
groundhog/general/__init__.py
groundhog/general/agsconversion.py
groundhog/general/parameter_mapping.py
groundhog/general/plotting.py
groundhog/general/soilprofile.py
groundhog/general/validation.py
groundhog/pipelinescables/__init__.py
groundhog/pipelinescables/stability/__init__.py
groundhog/pipelinescables/stability/penetration.py
groundhog/shallowfoundations/__init__.py
groundhog/shallowfoundations/capacity.py
groundhog/shallowfoundations/settlement.py
groundhog/shallowfoundations/stressdistribution.py
groundhog/siteinvestigation/__init__.py
groundhog/siteinvestigation/classification/__init__.py
groundhog/siteinvestigation/classification/categories.py
groundhog/siteinvestigation/classification/phaserelations.py
groundhog-0.15.0.dist-info/licenses/LICENSE
groundhog-0.15.0.dist-info/METADATA
groundhog-0.15.0.dist-info/WHEEL
groundhog-0.15.0.dist-info/top_level.txt
groundhog-0.15.0.dist-info/RECORD
