Metadata-Version: 2.4
Name: groundhog
Version: 0.15.0
Summary: Groundhog - A general-purpose geotechnical package
Home-page: https://github.com/snakesonabrain/groundhog
Download-URL: https://github.com/snakesonabrain/groundhog/archive/main.zip
Author: Bruno Stuyts
Author-email: bruno@pro-found.be
License: GNU GPLv3
Keywords: engineering,geotechnical
Classifier: Programming Language :: Python :: 3
Classifier: Operating System :: OS Independent
Requires-Python: >=3.7
License-File: LICENSE
Dynamic: author
Dynamic: author-email
Dynamic: classifier
Dynamic: description
Dynamic: download-url
Dynamic: home-page
Dynamic: keywords
Dynamic: license
Dynamic: license-file
Dynamic: requires-python
Dynamic: summary
